kikiutils_ssh/__init__.py
kiki_utils_ssh-1.0.2.dist-info/LICENSE.txt
kiki_utils_ssh-1.0.2.dist-info/METADATA
kiki_utils_ssh-1.0.2.dist-info/WHEEL
kiki_utils_ssh-1.0.2.dist-info/top_level.txt
kiki_utils_ssh-1.0.2.dist-info/zip-safe
kiki_utils_ssh-1.0.2.dist-info/RECORD
