Metadata-Version: 2.1
Name: kiki-utils-ssh
Version: 1.0.2
Summary: Utils ssh functions
Author: kiki-kanri
Author-email: a470666@gmail.com
Keywords: Utils
Classifier: License :: Freely Distributable
Requires-Python: >=3.8
License-File: LICENSE.txt
Requires-Dist: asyncssh
